{
  "id": "090cb843-2666-4ab3-8a4f-31b5c0225576",
  "prevId": "00000000-0000-0000-0000-000000000000",
  "version": "7",
  "dialect": "postgresql",
  "tables": {
    "public.gigs": {
      "name": "gigs",
      "schema": "",
      "columns": {
        "id": {
          "name": "id",
          "type": "serial",
          "primaryKey": true,
          "notNull": true
        },
        "title": {
          "name": "title",
          "type": "text",
          "primaryKey": false,
          "notNull": true
        },
        "location": {
          "name": "location",
          "type": "text",
          "primaryKey": false,
          "notNull": true
        },
        "date": {
          "name": "date",
          "type": "date",
          "primaryKey": false,
          "notNull": true
        },
        "description": {
          "name": "description",
          "type": "text",
          "primaryKey": false,
          "notNull": false
        },
        "start_time": {
          "name": "start_time",
          "type": "time",
          "primaryKey": false,
          "notNull": false
        },
        "end_time": {
          "name": "end_time",
          "type": "time",
          "primaryKey": false,
          "notNull": false
        },
        "price": {
          "name": "price",
          "type": "integer",
          "primaryKey": false,
          "notNull": false
        },
        "image": {
          "name": "image",
          "type": "text",
          "primaryKey": false,
          "notNull": false
        },
        "map_url": {
          "name": "map_url",
          "type": "text",
          "primaryKey": false,
          "notNull": false
        },
        "facebook_url": {
          "name": "facebook_url",
          "type": "text",
          "primaryKey": false,
          "notNull": false
        },
        "created_at": {
          "name": "created_at",
          "type": "timestamp",
          "primaryKey": false,
          "notNull": true,
          "default": "now()"
        },
        "updated_at": {
          "name": "updated_at",
          "type": "timestamp",
          "primaryKey": false,
          "notNull": true,
          "default": "now()"
        },
        "archived_at": {
          "name": "archived_at",
          "type": "timestamp",
          "primaryKey": false,
          "notNull": false
        }
      },
      "indexes": {
        "gigs_date_idx": {
          "name": "gigs_date_idx",
          "columns": [
            {
              "expression": "date",
              "isExpression": false,
              "asc": true,
              "nulls": "last"
            }
          ],
          "isUnique": false,
          "concurrently": false,
          "method": "btree",
          "with": {}
        },
        "gigs_title_date_place_uidx": {
          "name": "gigs_title_date_place_uidx",
          "columns": [
            {
              "expression": "title",
              "isExpression": false,
              "asc": true,
              "nulls": "last"
            },
            {
              "expression": "date",
              "isExpression": false,
              "asc": true,
              "nulls": "last"
            },
            {
              "expression": "location",
              "isExpression": false,
              "asc": true,
              "nulls": "last"
            }
          ],
          "isUnique": true,
          "concurrently": false,
          "method": "btree",
          "with": {}
        }
      },
      "foreignKeys": {},
      "compositePrimaryKeys": {},
      "uniqueConstraints": {},
      "policies": {},
      "checkConstraints": {
        "gigs_time_order_chk": {
          "name": "gigs_time_order_chk",
          "value": "\"gigs\".\"end_time\" IS NULL OR \"gigs\".\"start_time\" IS NULL OR \"gigs\".\"end_time\" > \"gigs\".\"start_time\""
        }
      },
      "isRLSEnabled": false
    }
  },
  "enums": {},
  "schemas": {},
  "sequences": {},
  "roles": {},
  "policies": {},
  "views": {},
  "_meta": {
    "columns": {},
    "schemas": {},
    "tables": {}
  }
}
